<?xml version="1.0" encoding="utf-8" ?>
<dwsync>
<file name="Autoloader.php" server="srv-datos/pruebasextincion/" local="131746751990000000" remote="131829534000000000" Dst="2" />
<file name="DocumentProperties.php" server="srv-datos/pruebasextincion/" local="131746751980000000" remote="131829534000000000" Dst="2" />
<file name="IOFactory.php" server="srv-datos/pruebasextincion/" local="131746751980000000" remote="131829534000000000" Dst="2" />
<file name="Media.php" server="srv-datos/pruebasextincion/" local="131746751980000000" remote="131829534000000000" Dst="2" />
<file name="Section.php" server="srv-datos/pruebasextincion/" local="131746751980000000" remote="131829534000000000" Dst="2" />
<file name="Style.php" server="srv-datos/pruebasextincion/" local="131746751980000000" remote="131829534000000000" Dst="2" />
<file name="Template.php" server="srv-datos/pruebasextincion/" local="131746751980000000" remote="131829534000000000" Dst="2" />
<file name="TOC.php" server="srv-datos/pruebasextincion/" local="131746751980000000" remote="131829534000000000" Dst="2" />
</dwsync>